motioneye/__init__.py
motioneye/cleanup.py
motioneye/config.py
motioneye/mediafiles.py
motioneye/meyectl.py
motioneye/mjpgclient.py
motioneye/monitor.py
motioneye/motionctl.py
motioneye/motioneye_init.py
motioneye/prefs.py
motioneye/remote.py
motioneye/sendmail.py
motioneye/sendtelegram.py
motioneye/server.py
motioneye/settings.py
motioneye/shell.py
motioneye/tasks.py
motioneye/template.py
motioneye/update.py
motioneye/uploadservices.py
motioneye/webhook.py
motioneye/wsswitch.py
motioneye/controls/__init__.py
motioneye/controls/diskctl.py
motioneye/controls/mmalctl.py
motioneye/controls/powerctl.py
motioneye/controls/smbctl.py
motioneye/controls/tzctl.py
motioneye/controls/v4l2ctl.py
motioneye/controls/wifictl.py
motioneye/extra/linux_init
motioneye/extra/motioneye.conf.sample
motioneye/extra/motioneye.systemd
motioneye/extra/motioneye.sysv
motioneye/handlers/__init__.py
motioneye/handlers/action.py
motioneye/handlers/base.py
motioneye/handlers/config.py
motioneye/handlers/log.py
motioneye/handlers/login.py
motioneye/handlers/main.py
motioneye/handlers/movie.py
motioneye/handlers/movie_playback.py
motioneye/handlers/picture.py
motioneye/handlers/power.py
motioneye/handlers/prefs.py
motioneye/handlers/relay_event.py
motioneye/handlers/update.py
motioneye/handlers/version.py
motioneye/locale/ar/LC_MESSAGES/motioneye.mo
motioneye/locale/bn/LC_MESSAGES/motioneye.mo
motioneye/locale/ca/LC_MESSAGES/motioneye.mo
motioneye/locale/cs/LC_MESSAGES/motioneye.mo
motioneye/locale/da/LC_MESSAGES/motioneye.mo
motioneye/locale/de/LC_MESSAGES/motioneye.mo
motioneye/locale/el/LC_MESSAGES/motioneye.mo
motioneye/locale/en/LC_MESSAGES/motioneye.mo
motioneye/locale/es/LC_MESSAGES/motioneye.mo
motioneye/locale/fi/LC_MESSAGES/motioneye.mo
motioneye/locale/fr/LC_MESSAGES/motioneye.mo
motioneye/locale/hi/LC_MESSAGES/motioneye.mo
motioneye/locale/hu/LC_MESSAGES/motioneye.mo
motioneye/locale/it/LC_MESSAGES/motioneye.mo
motioneye/locale/ja/LC_MESSAGES/motioneye.mo
motioneye-0.43.1.dist-info/licenses/LICENSE
motioneye-0.43.1.dist-info/METADATA
motioneye-0.43.1.dist-info/WHEEL
motioneye-0.43.1.dist-info/entry_points.txt
motioneye-0.43.1.dist-info/top_level.txt
motioneye-0.43.1.dist-info/RECORD
