Metadata-Version: 2.4
Name: motioneye
Version: 0.43.1
Summary: motioneye, a multilingual web interface for motion.
Author: Jean Michault
Author-email: Calin Crisan <ccrisan@gmail.com>
Maintainer-email: MichaIng <micha@dietpi.com>
License-Expression: GPL-3.0-or-later
Project-URL: Homepage, https://github.com/motioneye-project/motioneye
Project-URL: Source, https://github.com/motioneye-project/motioneye
Project-URL: Changelog, https://github.com/motioneye-project/motioneye/releases
Project-URL: Issue, https://github.com/motioneye-project/motioneye/issues
Keywords: motion,video,surveillance,frontend
Classifier: Operating System :: POSIX :: Linux
Classifier: Programming Language :: Python :: 3
Classifier: Topic :: Multimedia :: Video :: Capture
Requires-Python: >=3.7
License-File: LICENSE
Requires-Dist: tornado>=6.5.0
Requires-Dist: jinja2
Requires-Dist: pillow
Requires-Dist: pycurl
Requires-Dist: babel
Requires-Dist: boto3
Dynamic: license-file
